zlodziej_crawler/__init__.py
zlodziej_crawler/cache_helper.py
zlodziej_crawler/models.py
zlodziej_crawler/olx/__init__.py
zlodziej_crawler/olx/base_parser.py
zlodziej_crawler/olx/crawler.py
zlodziej_crawler/olx/get_offers.py
zlodziej_crawler/olx/iterator.py
zlodziej_crawler/olx/offers_parsing/__init__.py
zlodziej_crawler/olx/offers_parsing/base_offer.py
zlodziej_crawler/olx/offers_parsing/rent_offer.py
zlodziej_crawler/olx/parser_factory.py
zlodziej_crawler/olx/scrap_data.py
zlodziej_crawler/paths.py
zlodziej_crawler/tools/__init__.py
zlodziej_crawler/tools/export.py
zlodziej_crawler/tools/utilities.py
zlodziej_crawler/utilities.py
zlodziej_crawler-0.1.1.dist-info/entry_points.txt
zlodziej_crawler-0.1.1.dist-info/WHEEL
zlodziej_crawler-0.1.1.dist-info/METADATA
zlodziej_crawler-0.1.1.dist-info/RECORD
