Metadata-Version: 2.1
Name: zlodziej-crawler
Version: 0.1.1
Summary: 
Home-page: https://gitlab.com/mwozniak11121/zlodziej-crawler-public
Author: Mateusz Woźniak
Author-email: mwozniak11121@gmail.com
Requires-Python: >=3.7,<4.0
Classifier: Programming Language :: Python :: 3
Classifier: Programming Language :: Python :: 3.7
Classifier: Programming Language :: Python :: 3.8
Classifier: Programming Language :: Python :: 3.9
Requires-Dist: Pygments (>=2.7.1,<3.0.0)
Requires-Dist: Unidecode (>=1.1.1,<2.0.0)
Requires-Dist: bs4 (>=0.0.1,<0.0.2)
Requires-Dist: click (>=7.1.2,<8.0.0)
Requires-Dist: lxml (>=4.5.2,<5.0.0)
Requires-Dist: pydantic (>=1.6.1,<2.0.0)
Requires-Dist: python-dateutil (>=2.8.1,<3.0.0)
Requires-Dist: requests (>=2.24.0,<3.0.0)
Requires-Dist: tqdm (>=4.50.2,<5.0.0)
Project-URL: Repository, https://gitlab.com/mwozniak11121/zlodziej-crawler-public
